{
  "books": [
    {
      "id": 3,
      "class": 11,
      "authors": "Виленкин, Зубарева",
      "subject": "Английский язык"
    },
    {
      "id": 5,
      "class": 5,
      "authors": "Виленкин, Зубарева",
      "subject": "Химия"
    },
    {
      "id": 7,
      "class": 7,
      "authors": "Виленкин, Зубарева",
      "subject": "Литература"
    },
    {
      "id": 9,
      "class": 4,
      "authors": "Виленкин, Зубарева",
      "subject": "Литература"
    },
    {
      "class": "10",
      "authors": "Жохова Чесноков",
      "subject": "10",
      "id": 10
    },
    {
      "class": "",
      "authors": "",
      "subject": "",
      "id": 12
    }
  ],
  "users": [
    {
      "name": "1",
      "id": 1
    }
  ]
}